duro_rest/__init__.py
duro_rest/bom_client.py
duro_rest/duro_client.py
duro_rest/error.py
duro_rest-0.0.18.dist-info/LICENSE
duro_rest-0.0.18.dist-info/METADATA
duro_rest-0.0.18.dist-info/WHEEL
duro_rest-0.0.18.dist-info/RECORD
