Metadata-Version: 2.1
Name: duro-rest
Version: 0.0.18
Summary: An API client for the Duro REST API
Home-page: https://pypi.org/project/duro-rest/
License: MPL-2.0
Author: Augustus Mayo
Author-email: augustus@oxidecomputer.com
Maintainer: Augustus Mayo
Maintainer-email: augustus@oxidecomputer.com
Requires-Python: >=3.8,<4.0
Classifier: License :: OSI Approved
Classifier: License :: OSI Approved :: Mozilla Public License 2.0 (MPL 2.0)
Classifier: Programming Language :: Python :: 3
Classifier: Programming Language :: Python :: 3.8
Classifier: Programming Language :: Python :: 3.9
Classifier: Programming Language :: Python :: 3.10
Classifier: Programming Language :: Python :: 3.11
Requires-Dist: requests (>=2,<3)
